LICENSE
MANIFEST.in
README.md
runtests.py
setup.py
django_log_trigger.egg-info/PKG-INFO
django_log_trigger.egg-info/SOURCES.txt
django_log_trigger.egg-info/dependency_links.txt
django_log_trigger.egg-info/not-zip-safe
django_log_trigger.egg-info/requires.txt
django_log_trigger.egg-info/top_level.txt
log_trigger/__init__.py
log_trigger/helpers.py
log_trigger/settings.py
log_trigger/urls.py
log_trigger/views.py
requirements/install.txt
requirements/tests.txt